[{"source": "https://www.youtube.com/feeds/videos.xml?channel_id=UCC552Sd-3nyi_tk2BudLUzA", "title": "How Do Wildfires Affect Animals?", "description": "How did the Australia fires start? How will they change the Earth? Find out how they may impact you and how to help.\n\nDONATE: \nSave The Children: https://www.savethechildren.org.au/donate/more-ways-to-give/current-appeals/bushfire-emergency\nRed Cross: https://www.redcross.org.au/campaigns/disaster-relief-and-recovery-donate\nGIVIT: https://givit.worldsecuresystems.com/donate-funds\nNSW Rural Fire Service: https://www.rfs.nsw.gov.au/volunteer/support-your-local-brigade\n\nSubscribe: http:/bit.ly/asapsci\nCreated by: Mitchell Moffit and Gregory Brown\n\nFOLLOW US!\nGreg\nInstagram: https://instagram.com/whalewatchmeplz \nTwitter: https://twitter.com/whalewatchmeplz \n\nMitch\nInstagram: https://instagram.com/mitchellmoffit\nTwitter: https://twitter.com/mitchellmoffit \n\nAsapSCIENCE\nInstagram: https://instagram.com/asapscience \nFacebook: https://facebook.com/asapscience \nTwitter: https://twitter.com/asapscience\nTumblr: https://asapscience.tumblr.com \n\nSend us stuff!\nASAPSCIENCE INC.\nP.O. Box 93, Toronto P\nToronto, ON, M5S2S6", "link": "https://www.youtube.com/watch?v=jRdP6n1V2yU", "date_published": "2020-01-08 00:00:00+00:00", "persistent": false, "user": null, "language": "en-US"}]