[{"source": "https://www.youtube.com/feeds/videos.xml?channel_id=UCSbdMXOI_3HGiFviLZO6kNA", "title": "This NEW VR Headset is INSANE", "description": "Hello and welcome to TUES- I mean, WEDNESDAY NEWSDAY!\nYour number one resource for the entire weeks worth of VR news. This weeks news is more exciting than we have had in a long time, some of the most exciting parts are the brand new XR3 and VR3 headsets from Varjo, new Pimax headsets, and much more. Hope you enjoy!\n\nMy links: \nTwitch Stream TODAY!\nhttps://www.twitch.tv/thrilluwu\nJoin my discord for good times\nhttps://discord.gg/thrill\nPatreon link:Join\nhttps://www.patreon.com/Thrillseeker\nGAMERSUPPS Discount Code: THRILL\nhttp://gamersupps.gg/?afmc=thrill\n\n\n\nSources: \nhttps://www.theverge.com/2020/12/1/21720748/varjo-vr3-xr3-vr-ar-dual-resolution-headsets-price-shipping-specs\nhttps://www.roadtovr.com/varjo-xr-3-vr-3-announcement-specs-release-date-price/\nhttps://uploadvr.com/varjo-xr-3-vr-3-lidar/\nhttps://uploadvr.com/marvel-powers-united-shutting-down/\nhttps://www.roadtovr.com/openbci-brain-computer-interface-ar-vr-galea/\nhttps://www.roadtovr.com/oculus-quest-android-apps-carmack-debate/\nhttps://www.roadtovr.com/pimax-5k-super-vr-launch/\nhttps://www.pimax.com/\nhttps://www.youtube.com/watch?v=8OaSFppBx0Y\nhttps://www.youtube.com/watch?v=fyjJrF2gJ34", "link": "https://www.youtube.com/watch?v=kwFTxVPWgMU", "date_published": "2020-12-02 00:00:00+00:00", "persistent": false, "user": null, "language": "en-US"}]