[{"source": "https://www.youtube.com/feeds/videos.xml?channel_id=UC_7PqixGIdE-jjoHKMPYpGA", "title": "Najciekawsze odkrycia roku 2019", "description": "Patronite \u25ba https://patronite.pl/NaukowyBelkot \r\nMix audio \u25ba http://ratstudios.pl/\r\n\r\nJak co roku przychodzi czas na podsumowanie odkry\u0107 z ostatnich 12 miesi\u0119cy. Jak co roku w zacnym gronie. Jak co roku z \u017cyczeniami na nowy, 2020 rok. Wszystkiego dobrego!\r\n\r\n===\nTimeline:\n\n1:47 Miejsce 7.\n4:37 Miejsce 6. (https://www.youtube.com/c/KacperPitala)\n7:52 Miejsce 5. (https://www.youtube.com/channel/UCkPjHTuNd_ycm__29dXM3Nw)\n12:26 Miejsce 4. (https://www.youtube.com/c/Astrofaza)\n16:16 Miejsce 3. (https://www.youtube.com/channel/UCZgxE8WOvOmHNfMpv1otPxQ)\n18:32 Miejsce 2. (https://www.youtube.com/c/mowiacinaczej)\n20:35 Miejsce 1.\n\nSubskrypcja \u25ba https://youtube.com/c/UwagaNaukowyBelkot\r\nFacebook \u25ba https://facebook.com/UwagaNaukowyBelkot\r\nTwitter \u25ba https://twitter.com/NaukowyBelkot\r\nInstagram \u25ba https://www.instagram.com/NaukowyBelkot/\r\n\r\nWy\u0142\u0105cznie Naukowy Be\u0142kot \u25ba https://goo.gl/Do7VCc\r\nGrupa na facebooku \u25ba https://goo.gl/HP8J83", "link": "https://www.youtube.com/watch?v=6uziyARm1SU", "date_published": "2020-01-01 00:00:00+00:00", "persistent": false, "user": null, "language": "en-US"}]