[{"source": "https://www.globalsign.com", "title": "Why the Lawful Access to Encrypted Data Act is a Threat to your Privacy", "description": "Why the Lawful Access to Encrypted Data Act is a Threat to your Privacy", "link": "https://www.globalsign.com/en/blog/why-lawful-access-encrypted-data-act-threat-your-rights-and-privacy", "date_published": "2020-06-23 11:06:20+00:00", "persistent": true, "user": "rumpel", "language": "en", "tags": ["lawful access to encrypted data act", "privacy", "government control", "surveillance"]}]