[{"source": "https://www.youtube.com/feeds/videos.xml?channel_id=UCnxGkOGNMqQEUMvroOWps6Q", "title": "Best of the Week - April 12, 2020 - Joe Rogan Experience", "description": "#1457 w/Tim Dillon:\nhttps://www.youtube.com/watch?v=ig9yh8iVZWI\n\n#1458 w/Chris D'Elia:\nhttps://www.youtube.com/watch?v=98mh3jxcuxI\n\n#1459 w/Tom O'Neill:\nhttps://www.youtube.com/watch?v=J36xPWBLcG8\n\n#1460 w/Donnell Rawlings:\nhttps://www.youtube.com/watch?v=IXFlwSr5u_k", "link": "https://www.youtube.com/watch?v=Bt0nVl1Nlj4", "date_published": "2020-04-20 00:00:00+00:00", "persistent": false, "user": null, "language": "en-US"}]