[{"source": "https://www.youtube.com/feeds/videos.xml?channel_id=UCSiPjfAJBgbFlIUsxOWpK0w", "title": "Dreams // Fleetwood Mac // Sam Wilkes ft. POMPLAMOOSE", "description": "Gardenview out now, listen on Spotify (https://sptfy.com/gardenview) or wherever you listen to music.\n\n Here's Pomplamoose + Sam Wilkes cover of Fleetwood Mac's \"Dreams.\" We even got Jack to sing on the chorus :)\n\nOur album \u2018Invisible People\u2019 is now available EVERYWHERE! http://pomplamoose.com\n\nSave this song on Spotify: https://spoti.fi/2r3Yqkh\nFollow us on instagram: https://instagram.com/pomplamoosemusic\nBecome a patron of our music (to vote on the songs we cover and get merch and stuff like that): http://www.patreon.com/pomplamoose\n\nA cover of Dreams by Sam Wilkes & Pomplamoose.\n\nCREDITS\n\nLead Vocals: Nataly Dawn\nBackground Vocals: Jack Conte\nAll Instruments: Sam Wilkes\nMixing: Joey Genetti\nMastering: Mark Chalecki\nProducer: Sam Wilkes\n\nVIDEO CREDITS\nDirector: George Sloan\nDP: Ricky Chavez\nCamera Operators: Ricky Chavez & Sammy Rothman\nVideo Editor: Dominic Mercurio\n\nRecorded live at Kingsize Soundlabs in Eagle Rock.\n\nLYRICS\n\nNow here you go again, you say you want your freedom\nWell, who am I to keep you down?\nIt's only right that you should play the way you feel it\nBut listen carefully to the sound of your loneliness\n\nLike a heartbeat drives you mad\nIn the stillness of remembering what you had\nAnd what you lost\nAnd what you had\nAnd what you lost\n\nOh, thunder only happens when it's raining\nPlayers only love you when they're playing\nSay, women, they will come and they will go\nWhen the rain washes you clean, you'll know\nYou'll know\n\nNow here I go again, I see the crystal visions\nI keep my visions to myself\nIt's only me who wants to wrap around your dreams\nAnd have you any dreams you'd like to sell?\nDreams of loneliness\n\nLike a heartbeat drives you mad\nIn the stillness of remembering what you had\nAnd what you lost\nAnd what you had\nOh, what you lost\n\nThunder only happens when it's raining\nPlayers only love you when they're playing\nWomen, they will come and they will go\nWhen the rain washes you clean, you'll know\nOh, thunder only happens when it's raining\nPlayers only love you when they're playing\nSay, women, they will come and they will go\nWhen the rain washes you clean, you'll know\nYou'll know\nYou will know\nOh, you'll know\n\n#Pomplamoose #Dreams #FleetwoodMac #SamWilkes", "link": "https://www.youtube.com/watch?v=y3ztWQm577Q", "date_published": "2020-12-30 00:00:00+00:00", "persistent": false, "user": null, "language": "en-US"}]