[{"source": "https://www.youtube.com/feeds/videos.xml?channel_id=UCsM-ZFKD_8vlDjfhKRNUk1A", "title": "Mighty Oaks - koncert (MUZO.FM)", "description": "Mighty Oaks na \u017cywo w MUZO.FM. Mighty Oaks zagrali live w naszym studiu utowry: Tell Me What You're Thinking, Aileen i All Things Go. Piosenki pochodz\u0105 z p\u0142yty Mighty Oaks All Things Go. \n\nSubskrybuj nasz kana\u0142: http://www.muzo.tv\nFacebook: http://www.facebook.com/MUZO.FM\nFacebook: http://www.facebook.com/MUZO.TV\nFacebook Mighty Oaks: http://www.facebook.com/mightyoaksmusic\nInstagram Mighty Oaks: http://www.instagram.com/mightyoaksmusic\nInstagram: http://www.instagram.com/muzofm\nTwitter: http://twitter.com/muzo_fm\nStrona: http://www.muzo.fm", "link": "https://www.youtube.com/watch?v=0XCFNKtqkNA", "date_published": "2020-02-15 00:00:00+00:00", "persistent": false, "user": null, "language": "en-US"}, {"source": "https://www.youtube.com/feeds/videos.xml?channel_id=UCsM-ZFKD_8vlDjfhKRNUk1A", "title": "Kara\u015b/Rogucki - Bolesne strza\u0142y w serce - live MUZO.FM", "description": "Kara\u015b/Rogucki - Bolesne strza\u0142y w serce na \u017cywo w MUZO.FM. Piosenka Bolesne strza\u0142y w serce pochodzi z p\u0142yty duetu Kara\u015b/Rogucki Ostatni bastion romantyzmu. \n\nSubskrybuj nasz kana\u0142: http://www.muzo.tv\nFacebook: http://www.facebook.com/MUZO.FM\nFacebook: http://www.facebook.com/MUZO.TV\nFacebook Kara\u015b/Rogucki: http://www.facebook.com/karasrogucki\nInstagram Kara\u015b/Rogucki: http://www.instagram.com/karasrogucki\nInstagram: http://www.instagram.com/muzofm\nTwitter: http://twitter.com/muzo_fm\nStrona: http://www.muzo.fm\n\n\nKara\u015b/Rogucki - Bolesne strza\u0142y w serce - tekst \n\nDodaj mnie do swoich znajomych\nOdczytaj komunikat\nOznacz mnie na swojej linii czasu\nNa linii swojego \u017cycia\n\nNie mog\u0119 przy tobie oddycha\u0107\nOdjedziemy w osobnych przedzia\u0142ach\nOdjedziemy w przeciwnych kierunkach\nProsz\u0119 ci\u0119 nie utrudniaj\n\nNie wystarcza mi nic\n\nZnowu si\u0119 zatru\u0142em powietrzem\nZnowu jeste\u015b poza zasi\u0119giem\nDoda\u0142em lepsze zdj\u0119cie\nPrzyjrzyj si\u0119 \nPolub mnie \nZechciej\n\nTeraz b\u0119d\u0119 musia\u0142 ci\u0119 nosi\u0107\nDo ko\u0144ca miesi\u0105ca i wi\u0119cej\nRoznosi mnie gdy chodz\u0119 po mie\u015bcie\nBolesne strza\u0142y w serce\n\nNie wystarcza mi nic \n\n#popolsku", "link": "https://www.youtube.com/watch?v=15HWiYvUSis", "date_published": "2020-02-14 00:00:00+00:00", "persistent": false, "user": null, "language": "en-US"}]